{"trial_id": "19", "hyperparameters": {"space": [{"class_name": "Choice", "config": {"name": "units_1", "default": 64, "conditions": [], "values": [64, 80, 96, 128], "ordered": true}}, {"class_name": "Choice", "config": {"name": "dropout_1", "default": 0.2, "conditions": [], "values": [0.2, 0.3, 0.4], "ordered": true}}, {"class_name": "Choice", "config": {"name": "learning_rate", "default": 0.001, "conditions": [], "values": [0.001, 0.0005, 0.0001], "ordered": true}}], "values": {"units_1": 80, "dropout_1": 0.4, "learning_rate": 0.0005}}, "metrics": {"metrics": {"loss": {"direction": "min", "observations": [{"value": [0.038346245884895325], "step": 99}]}, "mae": {"direction": "min", "observations": [{"value": [0.149470716714859], "step": 99}]}, "val_loss": {"direction": "min", "observations": [{"value": [0.005600460804998875], "step": 99}]}, "val_mae": {"direction": "min", "observations": [{"value": [0.05609438568353653], "step": 99}]}}}, "score": 0.005600460804998875, "best_step": 99, "status": "COMPLETED", "message": null}